pgn2neo4j/__init__.py
pgn2neo4j/enums.py
pgn2neo4j/gamehandler.py
pgn2neo4j/gameparser.py
pgn2neo4j/queries.py
pgn2neo4j-0.0.2.dist-info/LICENSE
pgn2neo4j-0.0.2.dist-info/METADATA
pgn2neo4j-0.0.2.dist-info/WHEEL
pgn2neo4j-0.0.2.dist-info/top_level.txt
pgn2neo4j-0.0.2.dist-info/RECORD
