Metadata-Version: 2.1
Name: pgn2neo4j
Version: 0.0.2
Summary: Convert chess games (PGN:s) to a Neo4j database
Home-page: https://github.com/chess-opening-trainer/pgn2neo4j
Author: Anton Forsman
Classifier: Programming Language :: Python :: 3
Classifier: License :: OSI Approved :: MIT License
Classifier: Operating System :: OS Independent
Requires-Python: >=3.6
License-File: LICENSE
Requires-Dist: tqdm
Requires-Dist: chess
